timestamp_schema/__init__.py
timestamp_schema/timestamp_pb2.py
timestamp_schema-0.1.0.dist-info/METADATA
timestamp_schema-0.1.0.dist-info/WHEEL
timestamp_schema-0.1.0.dist-info/RECORD
