Metadata-Version: 2.1
Name: timestamp-schema
Version: 0.1.0
Summary: 
Author: danielroth
Author-email: daniel.roth@denktmit.de
Requires-Python: >=3.12,<4.0
Classifier: Programming Language :: Python :: 3
Classifier: Programming Language :: Python :: 3.12
Requires-Dist: grpcio (>=1.66.1,<2.0.0)
Requires-Dist: protobuf (>=5.28.2,<6.0.0)
